clear_html/__init__.py
clear_html/body_annotations.py
clear_html/clean.py
clear_html/html_embeddings.py
clear_html/lxml_utils.py
clear_html/py.typed
clear_html/formatted_text/__init__.py
clear_html/formatted_text/cleaner.py
clear_html/formatted_text/defs.py
clear_html/formatted_text/figures.py
clear_html/formatted_text/headings.py
clear_html/formatted_text/main.py
clear_html/formatted_text/utils.py
clear_html-0.4.1.dist-info/LICENSE
clear_html-0.4.1.dist-info/METADATA
clear_html-0.4.1.dist-info/WHEEL
clear_html-0.4.1.dist-info/top_level.txt
clear_html-0.4.1.dist-info/RECORD
