Metadata-Version: 2.1
Name: clear-html
Version: 0.4.1
Summary: Clean and normalize HTML.
Author-email: Zyte Group Ltd <info@zyte.com>
License: The MIT License (MIT)
Project-URL: Source, https://github.com/zytedata/clear-html
Classifier: Development Status :: 3 - Alpha
Classifier: Intended Audience :: Developers
Classifier: License :: OSI Approved :: BSD License
Classifier: Natural Language :: English
Classifier: Operating System :: OS Independent
Classifier: Programming Language :: Python :: 3
Classifier: Programming Language :: Python :: 3.8
Classifier: Programming Language :: Python :: 3.9
Classifier: Programming Language :: Python :: 3.10
Classifier: Programming Language :: Python :: 3.11
Classifier: Programming Language :: Python :: Implementation :: CPython
Requires-Python: >=3.8
License-File: LICENSE
Requires-Dist: attrs>=20.3.0
Requires-Dist: html-text>=0.5.2
Requires-Dist: lxml>=4.4.3
